rpi_ws281x/__init__.py
rpi_ws281x/rpi_ws281x_mock.py
rpi_ws281x_mock-0.2.2.dist-info/AUTHORS.rst
rpi_ws281x_mock-0.2.2.dist-info/LICENSE
rpi_ws281x_mock-0.2.2.dist-info/METADATA
rpi_ws281x_mock-0.2.2.dist-info/WHEEL
rpi_ws281x_mock-0.2.2.dist-info/top_level.txt
rpi_ws281x_mock-0.2.2.dist-info/RECORD
