Metadata-Version: 2.1
Name: rpi-ws281x-mock
Version: 0.2.2
Summary: This package mocks the behavior of the rpi-ws281x library
Home-page: https://github.com/HarmvZ/rpi_ws281x_mock
Author: Harm van Zeeland
Author-email: harm.van.zeeland@gmail.com
License: MIT license
Keywords: rpi_ws281x_mock
Platform: UNKNOWN
Classifier: Development Status :: 4 - Beta
Classifier: Intended Audience :: Developers
Classifier: License :: OSI Approved :: MIT License
Classifier: Natural Language :: English
Classifier: Programming Language :: Python :: 3
Classifier: Programming Language :: Python :: 3.6
Classifier: Programming Language :: Python :: 3.7
Classifier: Programming Language :: Python :: 3.8
Requires-Python: >=3.6
